[
  {
    "icon": "dashboard",
    "text": "Dashboard",
    "link": "/"
  },
  {
    "icon": "statistics",
    "text": "Statistieken",
    "link": "/statistics"
  },
  {
    "icon": "entity",
    "text": "Gebruikers",
    "link": "/users"
  },
  {
    "icon": "dialplans",
    "text": "Belplan",
    "link": "/dialplans"
  },
  {
    "icon": "admin",
    "text": "Modules",
    "link": "/modules"
  },
  {
    "icon": "phone",
    "text": "Gesprekken",
    "link": "/calls"
  },
  {
    "icon": "menu",
    "text": "Administratie",
    "link": "/administration"
  }
]
